genshin/__init__.py
genshin/traveller.py
genshin_lfk-1.0.0.dist-info/LICENSE
genshin_lfk-1.0.0.dist-info/METADATA
genshin_lfk-1.0.0.dist-info/WHEEL
genshin_lfk-1.0.0.dist-info/top_level.txt
genshin_lfk-1.0.0.dist-info/RECORD
