Metadata-Version: 2.1
Name: genshin-lfk
Version: 1.0.0
Summary: FKLiu's package
Home-page: https://github.com/pypa/sampleproject
Author: 刘富康(FKLiu)
Author-email: 1800016638@pku.edu.cn
License: UNKNOWN
Project-URL: Bug Tracker, https://github.com/pypa/sampleproject/issues
Platform: UNKNOWN
Classifier: Programming Language :: Python :: 3
Classifier: License :: OSI Approved :: MIT License
Classifier: Operating System :: OS Independent
Requires-Python: >=3.6
License-File: LICENSE
